    .source Main.j
    .class public Main
    .super java/lang/Object
.method public static main([Ljava/lang/String;)V
.limit stack 100
.limit locals 100
    iload 1
    ldc 243
    ldc 15
    istore 1
    iload 2
    iload 1
    ldc 1
    istore 1
    iload 3
    iload 1
    istore 1
    iload 4
    iload 2
    ldc 9
    istore 2
    iload 5
    iload 2
    istore 2
    iload 1
    iload 1
    iadd
    istore 1
    iload 2
    iload 2
    iadd
    istore 2
    iload 3
    iload 3
    idiv
    istore 3
    iload 1
    getstatic java/lang/System/out Ljava/io/PrintStream;
    swap
    invokevirtual java/io/PrintStream/println(I)V
    ldc " "
    getstatic java/lang/System/out Ljava/io/PrintStream;
    swap
    invokevirtual java/io/PrintStream/print(Ljava/lang/String;)V
    iload 2
    getstatic java/lang/System/out Ljava/io/PrintStream;
    swap
    invokevirtual java/io/PrintStream/println(I)V
    ldc " "
    getstatic java/lang/System/out Ljava/io/PrintStream;
    swap
    invokevirtual java/io/PrintStream/print(Ljava/lang/String;)V
    iload 3
    getstatic java/lang/System/out Ljava/io/PrintStream;
    swap
    invokevirtual java/io/PrintStream/println(I)V
    ldc " "
    getstatic java/lang/System/out Ljava/io/PrintStream;
    swap
    invokevirtual java/io/PrintStream/print(Ljava/lang/String;)V
    iload 4
    getstatic java/lang/System/out Ljava/io/PrintStream;
    swap
    invokevirtual java/io/PrintStream/println(I)V
    ldc " "
    getstatic java/lang/System/out Ljava/io/PrintStream;
    swap
    invokevirtual java/io/PrintStream/print(Ljava/lang/String;)V
    iload 5
    getstatic java/lang/System/out Ljava/io/PrintStream;
    swap
    invokevirtual java/io/PrintStream/println(I)V
    ldc "\n"
    getstatic java/lang/System/out Ljava/io/PrintStream;
    swap
    invokevirtual java/io/PrintStream/print(Ljava/lang/String;)V
    iload 5
    ldc 100
    ldc 255
    istore 5
    iload 5
    ldc 2
    ishl
    istore 5
    iload 5
    getstatic java/lang/System/out Ljava/io/PrintStream;
    swap
    invokevirtual java/io/PrintStream/println(I)V
    ldc "\n"
    getstatic java/lang/System/out Ljava/io/PrintStream;
    swap
    invokevirtual java/io/PrintStream/print(Ljava/lang/String;)V
    iload 5
    ldc 4
    iushr
    istore 5
    iload 5
    getstatic java/lang/System/out Ljava/io/PrintStream;
    swap
    invokevirtual java/io/PrintStream/println(I)V
    ldc "\n"
    getstatic java/lang/System/out Ljava/io/PrintStream;
    swap
    invokevirtual java/io/PrintStream/print(Ljava/lang/String;)V
    return
.end method
