    .source Main.j
    .class public Main
    .super java/lang/Object
.method public static main([Ljava/lang/String;)V
.limit stack 100
.limit locals 100
    ldc 0
    istore 1
    ldc 0
    istore 2
    ldc 10
    istore 3
    iload 1
    ldc 0
    isub
    ifeq L_cmp_0
    iconst_0
    goto L_cmp_1
    L_cmp_0:
    iconst_1
    L_cmp_1:
    iload 2
    ldc 0
    isub
    ifeq L_cmp_2
    iconst_0
    goto L_cmp_3
    L_cmp_2:
    iconst_1
    L_cmp_3:
    iand
    ifeq L_else_begin_1
        iload 1
        getstatic java/lang/System/out Ljava/io/PrintStream;
        swap
        invokevirtual java/io/PrintStream/print(I)V
        iload 2
        getstatic java/lang/System/out Ljava/io/PrintStream;
        swap
        invokevirtual java/io/PrintStream/print(I)V
        iload 3
        getstatic java/lang/System/out Ljava/io/PrintStream;
        swap
        invokevirtual java/io/PrintStream/print(I)V
        ldc "\n"
        getstatic java/lang/System/out Ljava/io/PrintStream;
        swap
        invokevirtual java/io/PrintStream/print(Ljava/lang/String;)V
    goto L_if_end_1
    L_else_begin_1:
    L_if_end_1:
    iload 3
    iload 2
    isub
    ldc 0
    isub
    ifge L_cmp_4
    iconst_0
    goto L_cmp_5
    L_cmp_4:
    iconst_1
    L_cmp_5:
    ifeq L_else_begin_2
        ldc "OK!"
        getstatic java/lang/System/out Ljava/io/PrintStream;
        swap
        invokevirtual java/io/PrintStream/print(Ljava/lang/String;)V
        ldc "\n"
        getstatic java/lang/System/out Ljava/io/PrintStream;
        swap
        invokevirtual java/io/PrintStream/print(Ljava/lang/String;)V
    goto L_if_end_2
    L_else_begin_2:
    L_if_end_2:
    iload 1
    ldc 0
    isub
    ifeq L_cmp_6
    iconst_0
    goto L_cmp_7
    L_cmp_6:
    iconst_1
    L_cmp_7:
    iload 2
    ldc 0
    isub
    ifne L_cmp_8
    iconst_0
    goto L_cmp_9
    L_cmp_8:
    iconst_1
    L_cmp_9:
    iand
    iload 3
    ldc 10
    isub
    ifeq L_cmp_10
    iconst_0
    goto L_cmp_11
    L_cmp_10:
    iconst_1
    L_cmp_11:
    ior
    ifeq L_else_begin_3
        ldc "test1"
        getstatic java/lang/System/out Ljava/io/PrintStream;
        swap
        invokevirtual java/io/PrintStream/print(Ljava/lang/String;)V
        ldc "\n"
        getstatic java/lang/System/out Ljava/io/PrintStream;
        swap
        invokevirtual java/io/PrintStream/print(Ljava/lang/String;)V
    goto L_if_end_3
    L_else_begin_3:
        iload 3
        ldc 10
        isub
        ifeq L_cmp_12
        iconst_0
        goto L_cmp_13
        L_cmp_12:
        iconst_1
        L_cmp_13:
        iload 1
        ldc 0
        isub
        ifne L_cmp_14
        iconst_0
        goto L_cmp_15
        L_cmp_14:
        iconst_1
        L_cmp_15:
        ior
        iload 1
        ldc 0
        isub
        ifeq L_cmp_16
        iconst_0
        goto L_cmp_17
        L_cmp_16:
        iconst_1
        L_cmp_17:
        iload 2
        ldc 0
        isub
        ifeq L_cmp_18
        iconst_0
        goto L_cmp_19
        L_cmp_18:
        iconst_1
        L_cmp_19:
        iand
        iload 3
        ldc 0
        isub
        ifeq L_cmp_20
        iconst_0
        goto L_cmp_21
        L_cmp_20:
        iconst_1
        L_cmp_21:
        iand
        iload 3
        ldc 10
        isub
        ifeq L_cmp_22
        iconst_0
        goto L_cmp_23
        L_cmp_22:
        iconst_1
        L_cmp_23:
        iload 1
        ldc 0
        isub
        ifeq L_cmp_24
        iconst_0
        goto L_cmp_25
        L_cmp_24:
        iconst_1
        L_cmp_25:
        ior
        iand
        iand
        ifeq L_else_begin_4
            ldc "test2"
            getstatic java/lang/System/out Ljava/io/PrintStream;
            swap
            invokevirtual java/io/PrintStream/print(Ljava/lang/String;)V
            ldc "\n"
            getstatic java/lang/System/out Ljava/io/PrintStream;
            swap
            invokevirtual java/io/PrintStream/print(Ljava/lang/String;)V
        goto L_if_end_4
        L_else_begin_4:
            ldc "test3"
            getstatic java/lang/System/out Ljava/io/PrintStream;
            swap
            invokevirtual java/io/PrintStream/print(Ljava/lang/String;)V
            ldc "\n"
            getstatic java/lang/System/out Ljava/io/PrintStream;
            swap
            invokevirtual java/io/PrintStream/print(Ljava/lang/String;)V
            iconst_1
            ifeq L_else_begin_5
                ldc "test4"
                getstatic java/lang/System/out Ljava/io/PrintStream;
                swap
                invokevirtual java/io/PrintStream/print(Ljava/lang/String;)V
                ldc "\n"
                getstatic java/lang/System/out Ljava/io/PrintStream;
                swap
                invokevirtual java/io/PrintStream/print(Ljava/lang/String;)V
            goto L_if_end_5
            L_else_begin_5:
            L_if_end_5:
        L_if_end_4:
    L_if_end_3:
    iconst_1
    ifeq L_else_begin_6
        ldc "test6"
        getstatic java/lang/System/out Ljava/io/PrintStream;
        swap
        invokevirtual java/io/PrintStream/print(Ljava/lang/String;)V
        ldc "\n"
        getstatic java/lang/System/out Ljava/io/PrintStream;
        swap
        invokevirtual java/io/PrintStream/print(Ljava/lang/String;)V
    goto L_if_end_6
    L_else_begin_6:
    L_if_end_6:
    ldc 0
    return
.end method
